pyenfra/__init__.py
pyenfra/functions.py
pyenfra/interpreters.py
pyenfra/plotting.py
pyenfra/utils.py
pyenfra-0.4.0.dist-info/licenses/LICENSE.md
pyenfra-0.4.0.dist-info/METADATA
pyenfra-0.4.0.dist-info/WHEEL
pyenfra-0.4.0.dist-info/top_level.txt
pyenfra-0.4.0.dist-info/RECORD
