Metadata-Version: 2.4
Name: pyenfra
Version: 0.4.0
Summary: A Python package for fractal and complexity analysis of time series.
Home-page: https://github.com/chrisrac/pyenfra
Author: Krzysztof Raczynski
Author-email: Krzysztof Raczynski <chrisr@gri.msstate.edu>
License: MIT
Project-URL: Homepage, https://github.com/chrisrac/pyenfra
Classifier: Programming Language :: Python :: 3
Classifier: Operating System :: OS Independent
Classifier: Topic :: Scientific/Engineering :: Information Analysis
Requires-Python: >=3.7
License-File: LICENSE.md
Requires-Dist: numpy>=1.17
Requires-Dist: scipy>=1.4
Requires-Dist: PyWavelets>=1.1.1
Requires-Dist: pyts>=0.12.0
Requires-Dist: matplotlib>=3.0
Provides-Extra: dev
Requires-Dist: pytest>=6.0; extra == "dev"
Requires-Dist: flake8; extra == "dev"
Requires-Dist: black; extra == "dev"
Dynamic: author
Dynamic: home-page
Dynamic: license-file
Dynamic: requires-python
